torchvision/_C.so
torchvision/__init__.py
torchvision/extension.py
torchvision/utils.py
torchvision/version.py
torchvision/datasets/__init__.py
torchvision/datasets/caltech.py
torchvision/datasets/celeba.py
torchvision/datasets/cifar.py
torchvision/datasets/cityscapes.py
torchvision/datasets/coco.py
torchvision/datasets/fakedata.py
torchvision/datasets/flickr.py
torchvision/datasets/folder.py
torchvision/datasets/hmdb51.py
torchvision/datasets/imagenet.py
torchvision/datasets/kinetics.py
torchvision/datasets/lsun.py
torchvision/datasets/mnist.py
torchvision/datasets/omniglot.py
torchvision/datasets/phototour.py
torchvision/datasets/sbd.py
torchvision/datasets/sbu.py
torchvision/datasets/semeion.py
torchvision/datasets/stl10.py
torchvision/datasets/svhn.py
torchvision/datasets/ucf101.py
torchvision/datasets/usps.py
torchvision/datasets/utils.py
torchvision/datasets/video_utils.py
torchvision/datasets/vision.py
torchvision/datasets/voc.py
torchvision/datasets/samplers/__init__.py
torchvision/datasets/samplers/clip_sampler.py
torchvision/io/__init__.py
torchvision/io/_video_opt.py
torchvision/io/video.py
torchvision/models/__init__.py
torchvision/models/_utils.py
torchvision/models/alexnet.py
torchvision/models/densenet.py
torchvision/models/googlenet.py
torchvision/models/inception.py
torchvision/models/mnasnet.py
torchvision/models/mobilenet.py
torchvision/models/resnet.py
torchvision/models/shufflenetv2.py
torchvision/models/squeezenet.py
torchvision/models/utils.py
torchvision/models/vgg.py
torchvision/models/detection/__init__.py
torchvision/models/detection/_utils.py
torchvision/models/detection/backbone_utils.py
torchvision/models/detection/faster_rcnn.py
torchvision/models/detection/generalized_rcnn.py
torchvision/models/detection/image_list.py
torchvision/models/detection/keypoint_rcnn.py
torchvision/models/detection/mask_rcnn.py
torchvision/models/detection/roi_heads.py
torchvision/models/detection/rpn.py
torchvision/models/detection/transform.py
rpi_torchvision-0.7.0.dist-info/LICENSE
rpi_torchvision-0.7.0.dist-info/METADATA
rpi_torchvision-0.7.0.dist-info/WHEEL
rpi_torchvision-0.7.0.dist-info/top_level.txt
rpi_torchvision-0.7.0.dist-info/RECORD
