Metadata-Version: 2.1
Name: rpi_torchvision
Version: 0.7.0
Summary: image and video datasets and models for torch deep learning
Platform: UNKNOWN
Requires-Dist: numpy
Requires-Dist: torch
Requires-Dist: pillow (>=4.1.1)
Provides-Extra: scipy
Requires-Dist: scipy ; extra == 'scipy'
